setup.py
altasetting/__init__.py
altasetting.egg-info/PKG-INFO
altasetting.egg-info/SOURCES.txt
altasetting.egg-info/dependency_links.txt
altasetting.egg-info/requires.txt
altasetting.egg-info/top_level.txt