Metadata-Version: 1.0
Name: altasetting
Version: 0.1.1
Summary: A python settings library
Home-page: http://github.com/felipelerena/altasetting
Author: Felipe Lerena
Author-email: felipelerena@gmail.com
License: UNKNOWN
Platform: UNKNOWN
